{
  "type": "FeatureCollection",
  "features": [
    {
      "type": "Feature",
      "properties": {
        "value": 1424.720703125
      },
      "geometry": {
        "type": "MultiPolygon",
        "value": 1424.720703125,
        "coordinates": [
          [
            [
              [
                8.121595786065939,
                51.4761524193319
              ],
              [
                8.121790262663524,
                51.47604065986841
              ],
              [
                8.122059757248735,
                51.4759943497613
              ],
              [
                8.122194673944165,
                51.47595118087403
              ],
              [
                8.122329251834003,
                51.475861656855415
              ],
              [
                8.122493057147352,
                51.475749943045734
              ],
              [
                8.122598746419214,
                51.47565747855425
              ],
              [
                8.122654019216554,
                51.475548705847
              ],
              [
                8.122868241004454,
                51.47536336466407
              ],
              [
                8.12291246197131,
                51.47534746927784
              ],
              [
                8.123061850683285,
                51.47514623333827
              ],
              [
                8.123137735589665,
                51.47503717886104
              ],
              [
                8.123204295655626,
                51.47494499802826
              ],
              [
                8.12332454387041,
                51.47474376334784
              ],
              [
                8.123407230174934,
                51.47459664709954
              ],
              [
                8.12343508092934,
                51.47454252929699
              ],
              [
                8.123532815825968,
                51.474341295875725
              ],
              [
                8.12361534474826,
                51.47414006308403
              ],
              [
                8.123676724760173,
                51.47396649546757
              ],
              [
                8.1236858529916,
                51.47393883092191
              ],
              [
                8.123739036644565,
                51.47373759938937
              ],
              [
                8.12378027284771,
                51.47353636848642
              ],
              [
                8.12380890806051,
                51.47333513821305
              ],
              [
                8.123823118303505,
                51.47313390856925
              ],
              [
                8.123820365786173,
                51.47293267955503
              ],
              [
                8.12379713593981,
                51.472731451170404
              ],
              [
                8.123758487811415,
                51.47253022341535
              ],
              [
                8.123686762178892,
                51.47232899628988
              ],
              [
                8.123676724760173,
                51.472304390345826
              ],
              [
                8.12358636711275,
                51.472127769794
              ],
              [
                8.123459024088845,
                51.4719265439277
              ],
              [
                8.123407230174934,
                51.471848389408294
              ],
              [
                8.123288030275035,
                51.47172531869098
              ],
              [
                8.123137735589665,
                51.47160682769149
              ],
              [
                8.122990938242452,
                51.47152409408384
              ],
              [
                8.122868241004454,
                51.47145660777151
              ],
              [
                8.122598746419214,
                51.47137495679688
              ],
              [
                8.122329251834003,
                51.47138785334228
              ],
              [
                8.122059757248735,
                51.471432578940316
              ],
              [
                8.121790262663524,
                51.47150377706181
              ],
              [
                8.121737695709726,
                51.47152409408384
              ],
              [
                8.121520768078312,
                51.47159988151863
              ],
              [
                8.121290408827463,
                51.47172531869098
              ],
              [
                8.121251273493044,
                51.47174999495315
              ],
              [
                8.121058009127722,
                51.4719265439277
              ],
              [
                8.120981778907804,
                51.47198542448366
              ],
              [
                8.12083877228747,
                51.472127769794
              ],
              [
                8.120712284322593,
                51.47225098487287
              ],
              [
                8.120663196076919,
                51.47232899628988
              ],
              [
                8.120530614221764,
                51.47253022341535
              ],
              [
                8.120442789737353,
                51.47267385499868
              ],
              [
                8.120416644662868,
                51.472731451170404
              ],
              [
                8.1203086862416,
                51.47293267955503
              ],
              [
                8.12020680331264,
                51.47313390856925
              ],
              [
                8.120173295152114,
                51.4731980786972
              ],
              [
                8.120121379920619,
                51.47333513821305
              ],
              [
                8.120059350458376,
                51.47353636848642
              ],
              [
                8.120008712795453,
                51.47373759938937
              ],
              [
                8.11996428534826,
                51.47393883092191
              ],
              [
                8.119930386491745,
                51.47414006308403
              ],
              [
                8.119905551749667,
                51.474341295875725
              ],
              [
                8.119903800566874,
                51.47437480034437
              ],
              [
                8.119900393139659,
                51.47454252929699
              ],
              [
                8.119903800566874,
                51.474708084981565
              ],
              [
                8.119905280162499,
                51.47474376334784
              ],
              [
                8.11993049201817,
                51.47494499802826
              ],
              [
                8.120080362155448,
                51.47514623333827
              ],
              [
                8.120099966125025,
                51.47534746927784
              ],
              [
                8.120173295152114,
                51.475402225350244
              ],
              [
                8.1203160743446,
                51.475548705847
              ],
              [
                8.120442789737353,
                51.47564332678166
              ],
              [
                8.120553272483335,
                51.475749943045734
              ],
              [
                8.120602143995995,
                51.47595118087403
              ],
              [
                8.120712284322593,
                51.47603342537979
              ],
              [
                8.120910746399119,
                51.4761524193319
              ],
              [
                8.120981778907804,
                51.47620546121678
              ],
              [
                8.121251273493044,
                51.47623237961841
              ],
              [
                8.121520768078312,
                51.47620843728241
              ],
              [
                8.121595786065939,
                51.4761524193319
              ]
            ]
          ]
        ]
      }
    }
  ]
}