{
  "type": "FeatureCollection",
  "features": [
    {
      "type": "Feature",
      "properties": {
        "value": 524.720703125
      },
      "geometry": {
        "type": "MultiPolygon",
        "value": 524.720703125,
        "coordinates": [
          [
            [
              [
                8.12171855130137,
                51.4761524193319
              ],
              [
                8.121790262663524,
                51.47611120908938
              ],
              [
                8.122059757248735,
                51.47609413266323
              ],
              [
                8.122329251834003,
                51.476050431513826
              ],
              [
                8.122462166444308,
                51.47595118087403
              ],
              [
                8.122598746419214,
                51.47585612821388
              ],
              [
                8.122740948058123,
                51.475749943045734
              ],
              [
                8.122789248794618,
                51.475548705847
              ],
              [
                8.122868241004454,
                51.47548036301842
              ],
              [
                8.123137735589665,
                51.475416928078225
              ],
              [
                8.123230754417477,
                51.47534746927784
              ],
              [
                8.123293528887388,
                51.47514623333827
              ],
              [
                8.123407230174934,
                51.4750363422541
              ],
              [
                8.123529558583783,
                51.47494499802826
              ],
              [
                8.12356480895204,
                51.47474376334784
              ],
              [
                8.123676724760173,
                51.474628238255995
              ],
              [
                8.123834765193237,
                51.47454252929699
              ],
              [
                8.123946219345385,
                51.474390522163596
              ],
              [
                8.123985266107496,
                51.474341295875725
              ],
              [
                8.124050690708003,
                51.47414006308403
              ],
              [
                8.124077911416379,
                51.47393883092191
              ],
              [
                8.124215713930624,
                51.473786780420916
              ],
              [
                8.124281578545379,
                51.47373759938937
              ],
              [
                8.124316590961598,
                51.47353636848642
              ],
              [
                8.124479111217425,
                51.47333513821305
              ],
              [
                8.124485208515893,
                51.47331775738682
              ],
              [
                8.124528894015725,
                51.47313390856925
              ],
              [
                8.124605230795567,
                51.47293267955503
              ],
              [
                8.124666593110902,
                51.472731451170404
              ],
              [
                8.124719717064863,
                51.47253022341535
              ],
              [
                8.124754703101104,
                51.47239603057185
              ],
              [
                8.124765041999524,
                51.47232899628988
              ],
              [
                8.124782986810118,
                51.472127769794
              ],
              [
                8.124845105553021,
                51.4719265439277
              ],
              [
                8.124865907870344,
                51.47172531869098
              ],
              [
                8.124880120858109,
                51.47152409408384
              ],
              [
                8.124880042098113,
                51.47132287010629
              ],
              [
                8.124873249922302,
                51.471121646758334
              ],
              [
                8.124858579110594,
                51.47092042403996
              ],
              [
                8.124830374497293,
                51.47071920195116
              ],
              [
                8.124779739158583,
                51.47051798049197
              ],
              [
                8.124754703101104,
                51.4704218151495
              ],
              [
                8.12472460954254,
                51.47031675966235
              ],
              [
                8.124641695978625,
                51.47011553946233
              ],
              [
                8.124544503511629,
                51.46991431989189
              ],
              [
                8.124485208515893,
                51.46981480067167
              ],
              [
                8.124419347760437,
                51.46971310095105
              ],
              [
                8.124285832716197,
                51.46951188263978
              ],
              [
                8.124215713930624,
                51.4694158641752
              ],
              [
                8.124140240517363,
                51.469310664958115
              ],
              [
                8.123967535161142,
                51.469109447906035
              ],
              [
                8.123946219345385,
                51.469087828187305
              ],
              [
                8.123747970413916,
                51.46890823148355
              ],
              [
                8.123676724760173,
                51.46884193290038
              ],
              [
                8.12340795762745,
                51.468707015690654
              ],
              [
                8.123407230174934,
                51.468706745084454
              ],
              [
                8.123393896996532,
                51.468707015690654
              ],
              [
                8.123137735589665,
                51.46871266650954
              ],
              [
                8.122868241004454,
                51.468793354161285
              ],
              [
                8.12260943557186,
                51.46890823148355
              ],
              [
                8.122598746419214,
                51.4689124148681
              ],
              [
                8.122329251834003,
                51.469057526697014
              ],
              [
                8.122237223093776,
                51.469109447906035
              ],
              [
                8.122059757248735,
                51.46920845209638
              ],
              [
                8.121877229367925,
                51.469310664958115
              ],
              [
                8.121790262663524,
                51.46936123469183
              ],
              [
                8.121575005123276,
                51.46951188263978
              ],
              [
                8.121520768078312,
                51.46954904576332
              ],
              [
                8.121322247279352,
                51.46971310095105
              ],
              [
                8.121251273493044,
                51.46976582083052
              ],
              [
                8.121087536175025,
                51.46991431989189
              ],
              [
                8.120981778907804,
                51.47001404793323
              ],
              [
                8.120894714552293,
                51.47011553946233
              ],
              [
                8.120735173900272,
                51.47031675966235
              ],
              [
                8.120712284322593,
                51.4703497289276
              ],
              [
                8.120629222711159,
                51.47051798049197
              ],
              [
                8.120508702510051,
                51.47071920195116
              ],
              [
                8.120442789737353,
                51.47083397811575
              ],
              [
                8.12042317090851,
                51.47092042403996
              ],
              [
                8.120385717222632,
                51.471121646758334
              ],
              [
                8.120231148878133,
                51.47132287010629
              ],
              [
                8.120173295152114,
                51.47146025655079
              ],
              [
                8.120152229155678,
                51.47152409408384
              ],
              [
                8.120070517146559,
                51.47172531869098
              ],
              [
                8.119992850124987,
                51.4719265439277
              ],
              [
                8.119908729440056,
                51.472127769794
              ],
              [
                8.119903800566874,
                51.472140080854885
              ],
              [
                8.119860527203514,
                51.47232899628988
              ],
              [
                8.119827700402283,
                51.47253022341535
              ],
              [
                8.119718205431383,
                51.472731451170404
              ],
              [
                8.119674082129364,
                51.47293267955503
              ],
              [
                8.119639878217782,
                51.47313390856925
              ],
              [
                8.119634305981634,
                51.47316724137323
              ],
              [
                8.11960978973994,
                51.47333513821305
              ],
              [
                8.11958774449539,
                51.47353636848642
              ],
              [
                8.119571776871311,
                51.47373759938937
              ],
              [
                8.119562247187929,
                51.47393883092191
              ],
              [
                8.11955980085392,
                51.47414006308403
              ],
              [
                8.119634305981634,
                51.4741956963275
              ],
              [
                8.119733934348176,
                51.474341295875725
              ],
              [
                8.119732423044468,
                51.47454252929699
              ],
              [
                8.119733954500902,
                51.47474376334784
              ],
              [
                8.119739848601881,
                51.47494499802826
              ],
              [
                8.119903800566874,
                51.47506742313844
              ],
              [
                8.119968905942898,
                51.47514623333827
              ],
              [
                8.119976134716836,
                51.47534746927784
              ],
              [
                8.120173295152114,
                51.475494692543464
              ],
              [
                8.120225943596722,
                51.475548705847
              ],
              [
                8.120442789737353,
                51.47571062931022
              ],
              [
                8.120483529180035,
                51.475749943045734
              ],
              [
                8.12050155007708,
                51.47595118087403
              ],
              [
                8.120712284322593,
                51.476108541438734
              ],
              [
                8.120785465291476,
                51.4761524193319
              ],
              [
                8.120981778907804,
                51.47629901209625
              ],
              [
                8.121251273493044,
                51.47630893800931
              ],
              [
                8.121520768078312,
                51.476300109493216
              ],
              [
                8.12171855130137,
                51.4761524193319
              ]
            ]
          ]
        ]
      }
    }
  ]
}